knock/__init__.py
knock/knockpy.py
knock/wordlist/wordlist.txt
knock_subdomains-7.0.2.dist-info/LICENSE
knock_subdomains-7.0.2.dist-info/METADATA
knock_subdomains-7.0.2.dist-info/WHEEL
knock_subdomains-7.0.2.dist-info/entry_points.txt
knock_subdomains-7.0.2.dist-info/top_level.txt
knock_subdomains-7.0.2.dist-info/RECORD
